{"0":{"fields":[{"type":"text","id":1,"formId":3,"label":"Name","adminLabel":"","isRequired":true,"size":"large","errorMessage":"","visibility":"visible","inputs":null,"description":"","allowsPrepopulate":false,"inputMask":false,"inputMaskValue":"","inputMaskIsCustom":false,"maxLength":"","labelPlacement":"","descriptionPlacement":"","subLabelPlacement":"","placeholder":"","cssClass":"","inputName":"","noDuplicates":false,"defaultValue":"","enableAutocomplete":false,"autocompleteAttribute":"","choices":"","conditionalLogic":"","productField":"","layoutGridColumnSpan":6,"enablePasswordInput":"","enableEnhancedUI":0,"layoutGroupId":"e99aa17c","multipleFiles":false,"maxFiles":"","calculationFormula":"","calculationRounding":"","enableCalculation":"","disableQuantity":false,"displayAllCategories":false,"useRichTextEditor":false,"errors":[],"fields":""},{"type":"email","id":3,"formId":3,"label":"Email","adminLabel":"","isRequired":true,"size":"large","errorMessage":"","visibility":"visible","inputs":null,"autocompleteAttribute":"email","description":"","allowsPrepopulate":false,"inputMask":false,"inputMaskValue":"","inputMaskIsCustom":false,"maxLength":"","labelPlacement":"","descriptionPlacement":"","subLabelPlacement":"","placeholder":"","cssClass":"","inputName":"","noDuplicates":false,"defaultValue":"","enableAutocomplete":false,"choices":"","conditionalLogic":"","productField":"","layoutGridColumnSpan":6,"emailConfirmEnabled":"","enableEnhancedUI":0,"layoutGroupId":"e99aa17c","multipleFiles":false,"maxFiles":"","calculationFormula":"","calculationRounding":"","enableCalculation":"","disableQuantity":false,"displayAllCategories":false,"useRichTextEditor":false,"fields":""},{"type":"select","id":4,"formId":3,"label":"Reason for Contacting","adminLabel":"","isRequired":true,"size":"large","errorMessage":"","visibility":"visible","validateState":true,"inputs":null,"choices":[{"text":"","value":"","isSelected":false,"price":""},{"text":"Question about the Program","value":"program","isSelected":false,"price":""},{"text":"Question about the Website","value":"website","isSelected":false,"price":""},{"text":"I have a website technical issue","value":"technical-issue","isSelected":false,"price":""}],"description":"","allowsPrepopulate":true,"inputMask":false,"inputMaskValue":"","inputMaskIsCustom":false,"maxLength":"","labelPlacement":"","descriptionPlacement":"","subLabelPlacement":"","placeholder":"","cssClass":"","inputName":"subject","noDuplicates":false,"defaultValue":"","enableAutocomplete":false,"autocompleteAttribute":"","conditionalLogic":"","productField":"","layoutGridColumnSpan":6,"enablePrice":"","enableEnhancedUI":0,"layoutGroupId":"c65face6","multipleFiles":false,"maxFiles":"","calculationFormula":"","calculationRounding":"","enableCalculation":"","disableQuantity":false,"displayAllCategories":false,"useRichTextEditor":false,"errors":[],"enableChoiceValue":true,"fields":""},{"type":"phone","id":5,"formId":3,"label":"Phone","adminLabel":"","isRequired":false,"size":"large","errorMessage":"","visibility":"visible","inputs":null,"phoneFormat":"international","autocompleteAttribute":"tel","description":"","allowsPrepopulate":false,"inputMask":false,"inputMaskValue":"","inputMaskIsCustom":false,"maxLength":"","labelPlacement":"","descriptionPlacement":"","subLabelPlacement":"","placeholder":"","cssClass":"","inputName":"","noDuplicates":false,"defaultValue":"","enableAutocomplete":false,"choices":"","conditionalLogic":"","productField":"","layoutGridColumnSpan":6,"enableEnhancedUI":0,"layoutGroupId":"c65face6","multipleFiles":false,"maxFiles":"","calculationFormula":"","calculationRounding":"","enableCalculation":"","disableQuantity":false,"displayAllCategories":false,"useRichTextEditor":false,"fields":""},{"type":"select","id":8,"formId":3,"label":"Please be more specific:","adminLabel":"","isRequired":true,"size":"large","errorMessage":"","visibility":"visible","validateState":true,"inputs":null,"choices":[{"text":"","value":"","isSelected":false,"price":""},{"text":"When trying to log in, it says invalid username or password","value":"invalid-login-credentials","isSelected":false,"price":""},{"text":"When trying to log in, the loading icon\/wheel just keeps spinning","value":"login-not-loading","isSelected":false,"price":""},{"text":"I'm not receiving a reset password email","value":"reset-password-email","isSelected":false,"price":""},{"text":"My email address has been flagged as spam","value":"flagged-as-spam","isSelected":false,"price":""},{"text":"Other","value":"other","isSelected":false,"price":""}],"description":"","allowsPrepopulate":true,"inputMask":false,"inputMaskValue":"","inputMaskIsCustom":false,"maxLength":"","labelPlacement":"","descriptionPlacement":"","subLabelPlacement":"","placeholder":"","cssClass":"","inputName":"detail","noDuplicates":false,"defaultValue":"","enableAutocomplete":false,"autocompleteAttribute":"","conditionalLogic":{"enabled":true,"actionType":"show","logicType":"all","rules":[{"fieldId":"4","operator":"is","value":"technical-issue"}]},"productField":"","layoutGridColumnSpan":12,"enablePrice":"","enableEnhancedUI":0,"layoutGroupId":"c11e7bb6","multipleFiles":false,"maxFiles":"","calculationFormula":"","calculationRounding":"","enableCalculation":"","disableQuantity":false,"displayAllCategories":false,"useRichTextEditor":false,"errors":[],"enableChoiceValue":true,"fields":""},{"type":"html","id":9,"formId":3,"label":"Inform about selection for login help","adminLabel":"","isRequired":false,"size":"large","errorMessage":"","visibility":"visible","inputs":null,"displayOnly":true,"description":"","allowsPrepopulate":false,"inputMask":false,"inputMaskValue":"","inputMaskIsCustom":false,"maxLength":"","labelPlacement":"","descriptionPlacement":"","subLabelPlacement":"","placeholder":"","cssClass":"","inputName":"","noDuplicates":false,"defaultValue":"","enableAutocomplete":false,"autocompleteAttribute":"","choices":"","conditionalLogic":{"enabled":true,"actionType":"show","logicType":"any","rules":[{"fieldId":"4","operator":"is","value":"program"},{"fieldId":"4","operator":"is","value":"website"}]},"content":"<div class=\"form-notice\">Note that if you are needing assistance logging in or registering, please select \"I have a website technical issue\" above.<\/div>","disableMargins":"","productField":"","layoutGridColumnSpan":12,"enableEnhancedUI":0,"layoutGroupId":"fe190e25","multipleFiles":false,"maxFiles":"","calculationFormula":"","calculationRounding":"","enableCalculation":"","disableQuantity":false,"displayAllCategories":false,"useRichTextEditor":false,"errors":[],"fields":""},{"type":"html","id":7,"formId":3,"label":"Let's try some things","adminLabel":"","isRequired":false,"size":"large","errorMessage":"","visibility":"visible","inputs":null,"displayOnly":true,"description":"","allowsPrepopulate":false,"inputMask":false,"inputMaskValue":"","inputMaskIsCustom":false,"maxLength":"","labelPlacement":"","descriptionPlacement":"","subLabelPlacement":"","placeholder":"","cssClass":"","inputName":"","noDuplicates":false,"defaultValue":"","enableAutocomplete":false,"autocompleteAttribute":"","choices":"","conditionalLogic":{"enabled":true,"actionType":"show","logicType":"all","rules":[{"fieldId":"8","operator":"is","value":"invalid-login-credentials"}]},"content":"<div class=\"form-notice\"><p>Bummer! Let's try a couple of things:<\/p>\n<ol>\n<li><strong>Double-check that your username\/email is correct.<\/strong> Sometimes we accidentally mistype our email address and it's not noticeable, or we forgot we used a different one for this site. Try your work email and your personal email.<\/li>\n<li><strong>Make sure your password is correct.<\/strong> It's easy to put the wrong password in. Double check that you are using the correct one and that it is typed in correctly with no spaces. <\/li>\n<li><strong>Try from a different browser.<\/strong> Occasionally there is an issue with a certain browser, browser version, or caching that causes issues with logging in. Internet Explorer tends to cause a lot of issues.<\/li>\n<li><strong>Try resetting your password.<\/strong> You can easily <a href=\"\/wp-login.php?action=lostpassword\" target=\"_blank\">reset your password by clicking here.<\/a><\/li>\n<li><strong>Still having issues?<\/strong> Continue filling out this form and make sure you include the email address you signed up with. Our webmaster will contact you shortly.<\/li>\n<\/ol><\/div>","disableMargins":"","productField":"","layoutGridColumnSpan":12,"enableEnhancedUI":0,"layoutGroupId":"5e92b1a4","multipleFiles":false,"maxFiles":"","calculationFormula":"","calculationRounding":"","enableCalculation":"","disableQuantity":false,"displayAllCategories":false,"useRichTextEditor":false,"errors":[],"fields":""},{"type":"html","id":12,"formId":3,"label":"Stuck Loading Login Description","adminLabel":"","isRequired":false,"size":"large","errorMessage":"","visibility":"visible","inputs":null,"displayOnly":true,"description":"","allowsPrepopulate":false,"inputMask":false,"inputMaskValue":"","inputMaskIsCustom":false,"maxLength":"","labelPlacement":"","descriptionPlacement":"","subLabelPlacement":"","placeholder":"","cssClass":"","inputName":"","noDuplicates":false,"defaultValue":"","enableAutocomplete":false,"autocompleteAttribute":"","choices":"","conditionalLogic":{"enabled":true,"actionType":"show","logicType":"all","rules":[{"fieldId":"8","operator":"is","value":"login-not-loading"}]},"content":"<div class=\"form-notice\">I'm sorry you're having this issue. This happens sometimes when passwords are either not strong enough or they contain a space in them. Few have had success trying a different browser, but it mostly gets resolved by <strong><a href=\"\/wp-login.php?action=lostpassword\">resetting your password<\/a><\/strong>. Try those possible solutions first.<\/div>","disableMargins":"","productField":"","layoutGridColumnSpan":12,"enableEnhancedUI":0,"layoutGroupId":"3e50555c","multipleFiles":false,"maxFiles":"","calculationFormula":"","calculationRounding":"","enableCalculation":"","disableQuantity":false,"displayAllCategories":false,"useRichTextEditor":false,"errors":[],"fields":""},{"type":"html","id":11,"formId":3,"label":"Not Receiving Password Reset Email Description","adminLabel":"","isRequired":false,"size":"large","errorMessage":"","visibility":"visible","inputs":null,"displayOnly":true,"description":"","allowsPrepopulate":false,"inputMask":false,"inputMaskValue":"","inputMaskIsCustom":false,"maxLength":"","labelPlacement":"","descriptionPlacement":"","subLabelPlacement":"","placeholder":"","cssClass":"","inputName":"","noDuplicates":false,"defaultValue":"","enableAutocomplete":false,"autocompleteAttribute":"","choices":"","conditionalLogic":{"enabled":true,"actionType":"show","logicType":"all","rules":[{"fieldId":"8","operator":"is","value":"reset-password-email"}]},"content":"<div class=\"form-notice\">Check if the email ended up in your spam\/junk folder. If it's not there, it could be that your organization has blocked it. If you are using a work or school email address, you can check with your IT department if any third-party software has quarantined it. If you are still having issues, continue with this form and we will reset it for you.<\/div>","disableMargins":"","productField":"","layoutGridColumnSpan":12,"enableEnhancedUI":0,"layoutGroupId":"b849917d","multipleFiles":false,"maxFiles":"","calculationFormula":"","calculationRounding":"","enableCalculation":"","disableQuantity":false,"displayAllCategories":false,"useRichTextEditor":false,"errors":[],"fields":""},{"type":"html","id":10,"formId":3,"label":"Flagged as spam","adminLabel":"","isRequired":false,"size":"large","errorMessage":"","visibility":"visible","inputs":null,"displayOnly":true,"description":"","allowsPrepopulate":false,"inputMask":false,"inputMaskValue":"","inputMaskIsCustom":false,"maxLength":"","labelPlacement":"","descriptionPlacement":"","subLabelPlacement":"","placeholder":"","cssClass":"","inputName":"","noDuplicates":false,"defaultValue":"","enableAutocomplete":false,"autocompleteAttribute":"","choices":"","conditionalLogic":{"enabled":true,"actionType":"show","logicType":"all","rules":[{"fieldId":"8","operator":"is","value":"flagged-as-spam"}]},"content":"<div class=\"form-notice\"><p>Oh no! This is often due to using a work or school computer that is has either been flagged or is behind a firewall. You can try a different computer or a mobile device on a network rather than the same internet provider's WiFi. We might also be able to add your organization's email domain to our whitelist to try and prevent it from happening again. Note that we cannot whitelist common email domains such as \"gmail.com\" since many spammers use those public email providers. If that doesn't work then there may be an issue with your email address in particular, whereas you'll need to use a different email address.<\/p>\n<\/div>","disableMargins":"","productField":"","layoutGridColumnSpan":12,"enableEnhancedUI":0,"layoutGroupId":"9b2ed1cb","multipleFiles":false,"maxFiles":"","calculationFormula":"","calculationRounding":"","enableCalculation":"","disableQuantity":false,"displayAllCategories":false,"useRichTextEditor":false,"errors":[],"fields":""},{"type":"textarea","id":6,"formId":3,"label":"Message","adminLabel":"","isRequired":true,"size":"large","errorMessage":"","visibility":"visible","inputs":null,"description":"","allowsPrepopulate":false,"inputMask":false,"inputMaskValue":"","inputMaskIsCustom":false,"maxLength":300,"labelPlacement":"","descriptionPlacement":"","subLabelPlacement":"","placeholder":"","cssClass":"","inputName":"","noDuplicates":false,"defaultValue":"","enableAutocomplete":false,"autocompleteAttribute":"","choices":"","conditionalLogic":"","productField":"","layoutGridColumnSpan":12,"useRichTextEditor":false,"enableEnhancedUI":0,"layoutGroupId":"4a72af7b","multipleFiles":false,"maxFiles":"","calculationFormula":"","calculationRounding":"","enableCalculation":"","disableQuantity":false,"displayAllCategories":false,"errors":[],"fields":""}],"button":{"type":"text","text":"","imageUrl":"","width":"auto","location":"bottom","layoutGridColumnSpan":12},"title":"Contact Us","description":"","version":"2.9.11","id":3,"markupVersion":2,"nextFieldId":13,"created_by":1,"is_active":true,"useCurrentUserAsAuthor":true,"postContentTemplateEnabled":false,"postTitleTemplateEnabled":false,"postTitleTemplate":"","postContentTemplate":"","lastPageButton":null,"pagination":null,"firstPageCssClass":null,"modified_by":1,"date_modified":"2025-07-09 18:18:54","labelPlacement":"top_label","descriptionPlacement":"below","validationPlacement":"below","subLabelPlacement":"below","requiredIndicator":"text","customRequiredIndicator":"(Required)","cssClass":"","saveButtonText":"Save & Continue","limitEntries":false,"limitEntriesCount":"","limitEntriesPeriod":"","limitEntriesMessage":"","scheduleForm":false,"scheduleStart":"","scheduleEnd":"","schedulePendingMessage":"","scheduleMessage":"","requireLogin":false,"requireLoginMessage":"","enableHoneypot":true,"honeypotAction":"spam","enableAnimation":true,"validationSummary":false,"deprecated":"","saveEnabled":"","save":{"enabled":false,"button":{"type":"link","text":"Save & Continue"}},"scheduleStartHour":"","scheduleStartMinute":"","scheduleStartAmpm":"","scheduleEndHour":"","scheduleEndMinute":"","scheduleEndAmpm":"","confirmations":[{"id":"686eae7993d07","name":"Default Confirmation","isDefault":true,"type":"message","message":"Thanks for contacting us! We will get in touch with you shortly.","url":"","pageId":"","queryString":""}],"notifications":[{"id":"686eb31f9048c","name":"Question about the Website","service":"wordpress","event":"form_submission","toType":"email","toEmail":"haberkorn@eri-wi.org","toField":"","routing":null,"fromName":"{Name:1}","from":"{admin_email}","replyTo":"{Email:3}","bcc":"kulow@eri-wi.org, gandy@eri-wi.org","subject":"New Help Request from {Name:1}: {Reason for Contacting:4}","message":"{all_fields}","disableAutoformat":false,"notification_conditional_logic_object":{"actionType":"show","logicType":"all","rules":[{"fieldId":"4","operator":"is","value":"website"}]},"notification_conditional_logic":"1","conditionalLogic":{"actionType":"show","logicType":"all","rules":[{"fieldId":"4","operator":"is","value":"website"}]},"to":"haberkorn@eri-wi.org","cc":"","enableAttachments":false},{"id":"686eb335f3df1","name":"Question about the Program","service":"wordpress","event":"form_submission","toType":"email","toEmail":"{admin_email}","toField":"","routing":null,"fromName":"{Name:1}","from":"{admin_email}","replyTo":"{Email:3}","bcc":"kulow@eri-wi.org, gandy@eri-wi.org","subject":"New Website Question from {Name:1}","message":"{all_fields}","disableAutoformat":false,"notification_conditional_logic_object":{"actionType":"show","logicType":"all","rules":[{"fieldId":"4","operator":"is","value":"program"}]},"notification_conditional_logic":"1","conditionalLogic":{"actionType":"show","logicType":"all","rules":[{"fieldId":"4","operator":"is","value":"program"}]},"to":"{admin_email}","cc":"","enableAttachments":false},{"id":"686eb37d23917","name":"Technical Issue","service":"wordpress","event":"form_submission","toType":"email","toEmail":"haberkorn@eri-wi.org","toField":"","routing":null,"fromName":"{Name:1}","from":"{admin_email}","replyTo":"{Email:3}","bcc":"kulow@eri-wi.org, gandy@eri-wi.org","subject":"New Help Request from {Name:1}: {Reason for Contacting:4}","message":"{all_fields}","disableAutoformat":false,"notification_conditional_logic_object":{"actionType":"show","logicType":"all","rules":[{"fieldId":"4","operator":"is","value":"technical-issue"}]},"notification_conditional_logic":"1","conditionalLogic":{"actionType":"show","logicType":"all","rules":[{"fieldId":"4","operator":"is","value":"technical-issue"}]},"to":"haberkorn@eri-wi.org","cc":"","enableAttachments":false}]},"version":"2.9.13"}